parseflow/__init__.py
parseflow/config.py
parseflow/docx/__init__.py
parseflow/docx/docx_parser.py
parseflow/docx/docx_utils.py
parseflow/excel/__init__.py
parseflow/excel/excel_parser.py
parseflow/excel/excel_utils.py
parseflow/images/__init__.py
parseflow/images/image_parser.py
parseflow/images/image_utils.py
parseflow/llms/__init__.py
parseflow/llms/classifier.py
parseflow/llms/ocr.py
parseflow/llms/summarizer.py
parseflow/llms/text_embedding.py
parseflow/models/__init__.py
parseflow/models/model_loader.py
parseflow/parser.py
parseflow/pdf/__init__.py
parseflow/pdf/pdf_parser.py
parseflow/pdf/pdf_utils.py
parseflow/utils/__init__.py
parseflow/utils/file_handler.py
parseflow/utils/json_formatter.py
parseflow/utils/logging_handler.py
parseflow-0.1.0.dist-info/LICENSE
parseflow-0.1.0.dist-info/METADATA
parseflow-0.1.0.dist-info/WHEEL
parseflow-0.1.0.dist-info/RECORD
